tholkaappiyam/__init__.py
tholkaappiyam/thol.py
tholkaappiyam-0.0.1.dist-info/LICENSE
tholkaappiyam-0.0.1.dist-info/METADATA
tholkaappiyam-0.0.1.dist-info/WHEEL
tholkaappiyam-0.0.1.dist-info/top_level.txt
tholkaappiyam-0.0.1.dist-info/RECORD
