Metadata-Version: 2.1
Name: tholkaappiyam
Version: 0.0.1
Summary: Tholkaappiyam - A library for Python to globalize the ancient text of the oldest language in the world, Tamil
Author-email: Aswin Venkat <aswinvenk8@gmail.com>, Sathishkumar Paramasivam <i18nsolutions@gmail.com>
Project-URL: Homepage, https://github.com/aswinvenk/tholkaappiyam
Project-URL: Bug Tracker, https://github.com/aswinvenk/tholkaappiyam/issues
Classifier: Programming Language :: Python :: 3
Classifier: License :: OSI Approved :: MIT License
Classifier: Operating System :: OS Independent
Classifier: Natural Language :: Tamil
Requires-Python: >=3.7
License-File: LICENSE
